pyJanus.cp311-win_amd64.pyd
python_janus-0.3.1.dist-info/LICENCE.md
python_janus-0.3.1.dist-info/METADATA
python_janus-0.3.1.dist-info/WHEEL
python_janus-0.3.1.dist-info/top_level.txt
python_janus-0.3.1.dist-info/RECORD
