Metadata-Version: 2.1
Name: python-janus
Version: 0.3.1
Summary: python bindings for Janus
Home-page: https://github.com/Boeing/pyjanus
Author: Alwin Wang
Author-email: 16846521+AlwinW@users.noreply.github.com
Requires-Python: >=3.7
License-File: LICENCE.md
Provides-Extra: test
Requires-Dist: pytest (>=6.0) ; extra == 'test'
